[
    {
      "id": 1,
      "title": "Skolkovo",
      "phone": "+79347563392",
      "email": "email@email.com",
      "address": "Москва",
      "description": "Школа управления СКОЛКОВО."
    },
    {
        "id": 2,
        "title": "Университет Сириус",
        "phone": "+79347593792",
        "email": "email@email.com",
        "address": "Сириус",
        "description": "Научно-технологический университет Сириус."
    },
    {
        "id": 3,
        "title": "Московский государственный университет (МГУ)",
        "phone": "+79341723392",
        "email": "email@email.com",
        "address": "Москва",
        "description": "Один из старейших и крупнейших классических университетов России."
    }
]